{
  "@context": [
    {
      "@version": 1.1,
      "@protected": true,
      "id": "@id",
      "type": "@type",
      "TwitterGeneralCredential": {
        "@id": "https://raw.githubusercontent.com/grmkris/checkmarks.io/main/schemas/v2/TwitterCredentials.json#TwitterGeneralCredential",
        "@context": {
          "@version": 1.1,
          "@protected": true,
          "id": "@id",
          "type": "@type",
          "twitter-vocab": "https://github.com/grmkris/checkmarks.io/blob/main/schemas/v2/Twitter.md",
          "xsd": "http://www.w3.org/2001/XMLSchema#",
          "username": {
            "@id": "twitter-vocab:username",
            "@type": "xsd:string"
          },
          "accountCreationDate": {
            "@id": "twitter-vocab:accountCreationDate",
            "@type": "xsd:date"
          }
        }
      },
      "TwitterFollowersCredential": {
        "@id": "https://raw.githubusercontent.com/grmkris/checkmarks.io/main/schemas/v2/TwitterCredentials.json#TwitterFollowersCredential",
        "@context": {
          "@version": 1.1,
          "@protected": true,
          "id": "@id",
          "type": "@type",
          "twitter-vocab": "https://github.com/grmkris/checkmarks.io/blob/main/schemas/v2/Twitter.md",
          "xsd": "http://www.w3.org/2001/XMLSchema#",
          "followersCount": {
            "@id": "twitter-vocab:followersCount",
            "@type": "xsd:integer"
          }
        }
      }
    }
  ]
}
